pydantic_settings_file_envar/__init__.py
pydantic_settings_file_envar/py.typed
pydantic_settings_file_envar-0.1.0.dist-info/LICENSE
pydantic_settings_file_envar-0.1.0.dist-info/METADATA
pydantic_settings_file_envar-0.1.0.dist-info/WHEEL
pydantic_settings_file_envar-0.1.0.dist-info/RECORD
