Metadata-Version: 2.1
Name: pydantic-settings-file-envar
Version: 0.1.0
Summary: Load pydantic settings from files named by _FILE suffix environment variables
Home-page: https://github.com/h4l/pydantic-settings-file-envar
License: MIT
Author: Hal Blackburn
Author-email: hwtb2@cam.ac.uk
Requires-Python: >=3.8,<4.0
Classifier: License :: OSI Approved :: MIT License
Classifier: Programming Language :: Python :: 3
Classifier: Programming Language :: Python :: 3.8
Classifier: Programming Language :: Python :: 3.9
Classifier: Programming Language :: Python :: 3.10
Classifier: Programming Language :: Python :: 3.11
Requires-Dist: exceptiongroup (>=1.1.3,<2.0.0) ; python_version < "3.11"
Requires-Dist: pydantic-settings (>=2.0.0,<3.0.0)
Project-URL: Repository, https://github.com/h4l/pydantic-settings-file-envar
